CHANGES.txt
LICENSE.txt
MANIFEST.in
README.txt
TODO.txt
setup.cfg
setup.py
Archive.egg-info/PKG-INFO
Archive.egg-info/SOURCES.txt
Archive.egg-info/dependency_links.txt
Archive.egg-info/top_level.txt
archive/__init__.py
archive/test/__init__.py
archive/test/__init__.pyc
archive/test/evil.tar.gz
archive/test/evil.zip
archive/test/foobar.tar
archive/test/foobar.tar.bz2
archive/test/foobar.tar.gz
archive/test/foobar.zip
archive/test/foobar_targz
archive/test/foobar_zip