Metadata-Version: 1.0
Name: Archive
Version: 0.3
Summary: Simple library that provides a common interface for extracting zip and tar archives.
Home-page: http://code.google.com/p/python-archive/
Author: Gary Wilson Jr.
Author-email: gary.wilson@gmail.com
License: LICENSE.txt
Platform: UNKNOWN
